ruleopt/__init__.py
ruleopt/aux_classes/__init__.py
ruleopt/aux_classes/aux_classes.c
ruleopt/aux_classes/aux_classes.cpython-313-x86_64-linux-musl.so
ruleopt/estimator/__init__.py
ruleopt/estimator/base.py
ruleopt/estimator/lightgbm_.py
ruleopt/estimator/xgboost_.py
ruleopt/estimator/sklearn_/__init__.py
ruleopt/estimator/sklearn_/base_sklearn.py
ruleopt/estimator/sklearn_/rug.py
ruleopt/estimator/sklearn_/rux.py
ruleopt/explainer/__init__.py
ruleopt/explainer/explainer.py
ruleopt/rule_cost/__init__.py
ruleopt/rule_cost/rule_cost.py
ruleopt/solver/__init__.py
ruleopt/solver/base.py
ruleopt/solver/cplex_solver.py
ruleopt/solver/gurobi_solver.py
ruleopt/solver/ortools_solver.py
ruleopt/solver/solver_utils.c
ruleopt/solver/solver_utils.cpython-313-x86_64-linux-musl.so
ruleopt/utils/__init__.py
ruleopt/utils/utils.py
ruleopt-1.1.4.dist-info/METADATA
ruleopt-1.1.4.dist-info/WHEEL
ruleopt-1.1.4.dist-info/top_level.txt
ruleopt-1.1.4.dist-info/RECORD
ruleopt-1.1.4.dist-info/licenses/LICENSE
