Metadata-Version: 2.4
Name: ruleopt
Version: 1.1.4
Summary: Optimization-Based Rule Learning for Classification
Author-email: Ilker Birbil <sibirbil@gmail.com>, Nursen Aydin <nursenaydin@gmail.com>, Ozgür Martin <ozgurmartin@gmail.com>, Samet Copur <sametcopur@yahoo.com>
License-Expression: BSD-3-Clause
Project-URL: Documentation, https://ruleopt.readthedocs.io/
Project-URL: Repository, https://github.com/sametcopur/ruleopt
Project-URL: Tracker, https://github.com/sametcopur/ruleopt/issues
Keywords: python,data-science,machine-learning,linear-programming,machine-learning-library,explainable-ai
Classifier: Programming Language :: Python :: 3
Classifier: Operating System :: OS Independent
Requires-Python: >=3.9
License-File: LICENSE
Requires-Dist: scikit-learn>=1.7.2
Requires-Dist: numpy>=2.2.3
Requires-Dist: pandas>=2.3
Requires-Dist: ortools>=9.11.4210
Dynamic: license-file
